Topsis_ShivomChawla_101916036/__init__.py
Topsis_ShivomChawla_101916036-2.0.0.dist-info/LICENSE
Topsis_ShivomChawla_101916036-2.0.0.dist-info/METADATA
Topsis_ShivomChawla_101916036-2.0.0.dist-info/WHEEL
Topsis_ShivomChawla_101916036-2.0.0.dist-info/top_level.txt
Topsis_ShivomChawla_101916036-2.0.0.dist-info/RECORD
