Metadata-Version: 2.1
Name: Topsis-ShivomChawla-101916036
Version: 2.0.0
Summary: A small package to work with topsis
Home-page: https://github.com/shivom2k/Topsis_ShivomChawla_101916036
Author: Shivom
Author-email: schawla_be19@thapar.edu
License: UNKNOWN
Platform: UNKNOWN
Classifier: Programming Language :: Python :: 3
Classifier: License :: OSI Approved :: MIT License
Classifier: Operating System :: OS Independent
License-File: LICENSE
